Metadata-Version: 2.1
Name: my-names2-krisss
Version: 1.0.0.0
Summary: Generate random names with length
Author: krisss993
Author-email: kristopherp994@gmail.com
Keywords: random names
